molecule_generation/__init__.py
molecule_generation/version.py
molecule_generation/wrapper.py
molecule_generation/chem/__init__.py
molecule_generation/chem/atom_feature_utils.py
molecule_generation/chem/molecule_dataset_utils.py
molecule_generation/chem/motif_utils.py
molecule_generation/chem/rdkit_helpers.py
molecule_generation/chem/topology_features.py
molecule_generation/chem/valence_constraints.py
molecule_generation/cli/__init__.py
molecule_generation/cli/cli.py
molecule_generation/cli/encode.py
molecule_generation/cli/preprocess.py
molecule_generation/cli/sample.py
molecule_generation/cli/train.py
molecule_generation/cli/visualise.py
molecule_generation/dataset/__init__.py
molecule_generation/dataset/in_memory_trace_dataset.py
molecule_generation/dataset/jsonl_abstract_trace_dataset.py
molecule_generation/dataset/jsonl_cgvae_trace_dataset.py
molecule_generation/dataset/jsonl_graph_properties_dataset.py
molecule_generation/dataset/jsonl_moler_trace_dataset.py
molecule_generation/dataset/trace_dataset.py
molecule_generation/dataset/trace_sample.py
molecule_generation/layers/__init__.py
molecule_generation/layers/cgvae_decoder.py
molecule_generation/layers/graph_property_predictor.py
molecule_generation/layers/moler_decoder.py
molecule_generation/models/__init__.py
molecule_generation/models/cgvae.py
molecule_generation/models/moler_base_model.py
molecule_generation/models/moler_generator.py
molecule_generation/models/moler_vae.py
molecule_generation/preprocessing/__init__.py
molecule_generation/preprocessing/cgvae_generation_trace.py
molecule_generation/preprocessing/data_conversion_utils.py
molecule_generation/preprocessing/generation_order.py
molecule_generation/preprocessing/graph_sample.py
molecule_generation/preprocessing/moler_generation_trace.py
molecule_generation/preprocessing/preprocess.py
molecule_generation/test/__init__.py
molecule_generation/test/conftest.py
molecule_generation/test/dataset/test_jsonl_cgvae_trace_dataset_preprocessing.py
molecule_generation-0.4.1.dist-info/LICENSE
molecule_generation-0.4.1.dist-info/METADATA
molecule_generation-0.4.1.dist-info/WHEEL
molecule_generation-0.4.1.dist-info/entry_points.txt
molecule_generation-0.4.1.dist-info/top_level.txt
molecule_generation-0.4.1.dist-info/RECORD
