Metadata-Version: 2.1
Name: molecule_generation
Version: 0.4.1
Summary: Implementations of deep generative models of molecules.
Home-page: https://github.com/microsoft/molecule-generation/
Author: Krzysztof Maziarz
Author-email: krzysztof.maziarz@microsoft.com
License: MIT
Classifier: License :: OSI Approved :: MIT License
Classifier: Operating System :: OS Independent
Classifier: Programming Language :: Python :: 3
Classifier: Programming Language :: Python :: 3.7
Classifier: Programming Language :: Python :: 3.8
Classifier: Programming Language :: Python :: 3.9
Classifier: Programming Language :: Python :: 3.10
Classifier: Topic :: Scientific/Engineering :: Artificial Intelligence
Requires-Python: >=3.7
License-File: LICENSE
Requires-Dist: dpu-utils >=0.2.13
Requires-Dist: more-itertools
Requires-Dist: numpy >=1.19.2
Requires-Dist: protobuf <4.21
Requires-Dist: scikit-learn >=0.24.1
Requires-Dist: tensorflow <2.10,>=2.1
Requires-Dist: tf2-gnn >=2.13.0
